{
    "interests": [
        "Welsh Affairs", 
        "Welfare", 
        "Economic Development"
    ], 
    "committees": [
        {
            "to": null, 
            "from": "2010-10-20", 
            "name": "Panel of Chairs"
        }, 
        {
            "to": null, 
            "from": "2010-07-12", 
            "name": "Energy and Climate Change Committee"
        }
    ], 
    "display_name": "Albert Owen", 
    "gender": "male", 
    "party_colour": "#cc0000", 
    "party_name": "Labour", 
    "slug": "albert-owen", 
    "id": "1474"
}