{
    "interests": [
        "Employment", 
        "Education And Training", 
        "Childcare", 
        "Welfare To Work", 
        "Family Friendly Employment", 
        "Crime", 
        "Anti-Social Behaviour", 
        "House Of Commons Modernisation", 
        "Education"
    ], 
    "committees": [], 
    "gender": "female", 
    "id": "389", 
    "party": {
        "colour": "#cc0000", 
        "name": "Labour"
    }, 
    "display_name": "Caroline Flint", 
    "slug": "caroline-flint"
}