{
    "interests": [
        "Disability", 
        "Broadcasting", 
        "Welfare Reform", 
        "Social Inclusion", 
        "Genetics", 
        "Pensions", 
        "Equalities"
    ], 
    "committees": [
        {
            "to": null, 
            "from": "2001-07-16", 
            "name": "Work and Pensions Committee"
        }, 
        {
            "to": null, 
            "from": "2010-07-19", 
            "name": "Liaison Committee (Commons)"
        }
    ], 
    "display_name": "Dame  Anne Begg", 
    "gender": "female", 
    "party_colour": "#cc0000", 
    "party_name": "Labour", 
    "slug": "dame-anne-begg", 
    "id": "572"
}