{
    "interests": [
        "Nhs", 
        "Home Affairs", 
        "Agriculture", 
        "Environment", 
        "Energy", 
        "Housing", 
        "Education", 
        "Alcohol Abuse And Under-Age Drinking", 
        "European Union", 
        "Defence"
    ], 
    "committees": [
        {
            "to": null, 
            "from": "2001-06-26", 
            "name": "Panel of Chairs"
        }
    ], 
    "display_name": "Mr Jim Hood", 
    "gender": "male", 
    "party_colour": "#cc0000", 
    "party_name": "Labour", 
    "slug": "mr-jim-hood", 
    "id": "582"
}